LICENSE
MANIFEST.in
README.rst
patois.py
requirements.txt
setup.cfg
setup.py
test_patois.py
docs/Makefile
docs/conf.py
docs/index.rst
patois.egg-info/PKG-INFO
patois.egg-info/SOURCES.txt
patois.egg-info/dependency_links.txt
patois.egg-info/not-zip-safe
patois.egg-info/top_level.txt