Metadata-Version: 1.1
Name: patois
Version: 0.1.0
Summary: Python VM compatibility library
Home-page: http://pypi.python.org/pypi/patois/
Author: Hank Gay
Author-email: hank@realultimateprogramming.com
License: The MIT License (MIT)
